arglogger/__init__.py
arglogger/backends.py
arglogger/tracker.py
arglogger/utils.py
arglogger-0.1.1.dist-info/licenses/LICENSE
arglogger-0.1.1.dist-info/METADATA
arglogger-0.1.1.dist-info/WHEEL
arglogger-0.1.1.dist-info/top_level.txt
arglogger-0.1.1.dist-info/RECORD
