Metadata-Version: 2.4
Name: arglogger
Version: 0.1.1
Summary: A package for logging experiment results with automatic table generation from argparse configurations
Author-email: Your Name <your.email@example.com>
License: MIT
Project-URL: Homepage, https://github.com/MinsGoing/arglogger
Project-URL: Repository, https://github.com/MinsGoing/arglog.git
Project-URL: Issues, https://github.com/MinsGoing/arglog/issues
Classifier: Development Status :: 3 - Alpha
Classifier: Intended Audience :: Developers
Classifier: License :: OSI Approved :: MIT License
Classifier: Operating System :: OS Independent
Classifier: Programming Language :: Python :: 3
Classifier: Programming Language :: Python :: 3.7
Classifier: Programming Language :: Python :: 3.8
Classifier: Programming Language :: Python :: 3.9
Classifier: Programming Language :: Python :: 3.10
Classifier: Programming Language :: Python :: 3.11
Classifier: Topic :: Scientific/Engineering
Classifier: Topic :: Database
Requires-Python: >=3.7
License-File: LICENSE
Requires-Dist: pandas>=1.0.0
Provides-Extra: dev
Requires-Dist: pytest>=6.0; extra == "dev"
Requires-Dist: pytest-cov; extra == "dev"
Requires-Dist: black; extra == "dev"
Requires-Dist: flake8; extra == "dev"
Dynamic: license-file
